MANIFEST.in
README.txt
contributors.txt
setup.py
examples/sliderapp_example.py
mplgbw/__init__.py
mplgbw/fancysliders.py
mplgbw.egg-info/PKG-INFO
mplgbw.egg-info/SOURCES.txt
mplgbw.egg-info/dependency_links.txt
mplgbw.egg-info/top_level.txt