Metadata-Version: 1.0
Name: mplgbw
Version: 0.1
Summary: UNKNOWN
Home-page: https://bitbucket.org/ahojukka5/mplgbw
Author: Jukka Aho
Author-email: ahojukka5@gmail.com
License: FreeBSD
Platform: UNKNOWN
